nocamel/__init__.py
nocamel/converters.py
nocamel-2025.1.0.dist-info/METADATA
nocamel-2025.1.0.dist-info/WHEEL
nocamel-2025.1.0.dist-info/entry_points.txt
nocamel-2025.1.0.dist-info/RECORD
