Metadata-Version: 2.4
Name: nocamel
Version: 2025.1.0
Summary: Born from a hatred of camel case manuscript titles.
Author-email: Jesse Charlton <57236497+jchar32@users.noreply.github.com>
License-Expression: MIT
Keywords: camel case,snake case,string converter,title case
Classifier: Development Status :: 3 - Alpha
Classifier: Programming Language :: Python :: 3.10
Requires-Python: >=3.10
Requires-Dist: click
Requires-Dist: pyperclip>=1.9.0
